AUTHORS.rst
CONTRIBUTING.rst
HISTORY.rst
LICENSE
MANIFEST.in
README.rst
setup.cfg
setup.py
amt/__init__.py
amt/client.py
amt/hostdb.py
amt/wsman.py
amt.egg-info/PKG-INFO
amt.egg-info/SOURCES.txt
amt.egg-info/dependency_links.txt
amt.egg-info/not-zip-safe
amt.egg-info/requires.txt
amt.egg-info/top_level.txt
bin/amtctrl
docs/Makefile
docs/authors.rst
docs/conf.py
docs/contributing.rst
docs/history.rst
docs/index.rst
docs/installation.rst
docs/make.bat
docs/readme.rst
docs/usage.rst
tests/__init__.py
tests/test_hostdb.py
tests/test_wsman.py