Metadata-Version: 1.1
Name: amt
Version: 0.6.0
Summary: Tools for interacting with Intel's AMT
Home-page: https://github.com/sdague/amt
Author: Sean Dague
Author-email: sean@dague.net
License: Apache
Keywords: amt
Platform: UNKNOWN
Classifier: Development Status :: 4 - Beta
Classifier: Intended Audience :: Developers
Classifier: License :: OSI Approved :: Apache Software License
Classifier: Natural Language :: English
Classifier: Programming Language :: Python :: 2
Classifier: Programming Language :: Python :: 2.7
Classifier: Programming Language :: Python :: 3
Classifier: Programming Language :: Python :: 3.4
